<?xml version="1.0" encoding="utf-8"?>
<management>
<fact>
  
<catfact>Cat's are felines</catfact>

</fact>
<fact>
  
<catfact>cat's are domesticated</catfact>

  <pageTitle>Cat Facts</pageTitle>
</fact>


  <fact>
  
<catfact>Cat's come in many shapes and sizes</catfact>

</fact>

  <fact>
  
<catfact>Black cat's are considered unlucky</catfact>
    

</fact>

  <fact>
  
<catfact>Many also consider orange cat's dumb</catfact>

</fact>
  
</management>





